{"format":2,"version":"5.0.3","globals":"7527df52019cd66aa8b9e50e1720726a","files":{"abay___init___py":{"hash":"af9d0d0de0ea3b71d198bc63f1499a7d","index":{"nums":[1,0,0,0,0,0,0],"html_filename":"abay___init___py.html","relative_filename":"abay/__init__.py"}},"abay_admin_py":{"hash":"6c434300fb151ebcf5d1aebcef77a0e3","index":{"nums":[1,11,0,0,0,0,0],"html_filename":"abay_admin_py.html","relative_filename":"abay/admin.py"}},"abay_decorators_py":{"hash":"78839f646a659a8d3cf18b74d1a6855e","index":{"nums":[1,2,0,2,0,0,0],"html_filename":"abay_decorators_py.html","relative_filename":"abay/decorators.py"}},"abay_forms_py":{"hash":"367c8e585ad8da6d33d05b5d9342eea1","index":{"nums":[1,33,0,33,0,0,0],"html_filename":"abay_forms_py.html","relative_filename":"abay/forms.py"}},"abay_models_py":{"hash":"48703c61d528837bccd46526409ab435","index":{"nums":[1,97,0,40,0,0,0],"html_filename":"abay_models_py.html","relative_filename":"abay/models.py"}},"abay_views_py":{"hash":"657999870879cb8c7f7be45343626782","index":{"nums":[1,90,0,90,0,0,0],"html_filename":"abay_views_py.html","relative_filename":"abay/views.py"}},"online_shopping___init___py":{"hash":"af9d0d0de0ea3b71d198bc63f1499a7d","index":{"nums":[1,0,0,0,0,0,0],"html_filename":"online_shopping___init___py.html","relative_filename":"online_shopping/__init__.py"}}}}